torchmeter/__cli__.py
torchmeter/__init__.py
torchmeter/_stat_numeric.py
torchmeter/config.py
torchmeter/core.py
torchmeter/display.py
torchmeter/engine.py
torchmeter/py.typed
torchmeter/statistic.py
torchmeter/unit.py
torchmeter/utils.py
torchmeter-0.1.0.dist-info/licenses/LICENSE
torchmeter-0.1.0.dist-info/METADATA
torchmeter-0.1.0.dist-info/WHEEL
torchmeter-0.1.0.dist-info/entry_points.txt
torchmeter-0.1.0.dist-info/top_level.txt
torchmeter-0.1.0.dist-info/RECORD
