Metadata-Version: 2.4
Name: torchmeter
Version: 0.1.0
Summary: "Torchmeter ⏲️:  Your all-in-one tool for Pytorch model analysis, measuring Params, FLOPs/MACs(aka. MACC or MADD), Memory cost, Inference time and Throughput 🚀"
Home-page: https://github.com/TorchMeter
Download-URL: https://pypi.org/project/torchmeter
Author: Ahzyuan
Author-email: hzy_dev@yeah.net
License: AGPL-3.0
Project-URL: Source Code, https://github.com/TorchMeter/torchmeter
Project-URL: Documentation, https://docs.torchmeter.top/latest/
Keywords: pytorch,model-analysis,parameter-estimation,inference-throughput,memory-estimation,calculation-estimation
Classifier: License :: OSI Approved :: GNU Affero General Public License v3
Classifier: Development Status :: 4 - Beta
Classifier: Topic :: Software Development :: Libraries :: Python Modules
Classifier: Programming Language :: Python :: Implementation :: CPython
Classifier: Programming Language :: Python :: Implementation :: PyPy
Classifier: Programming Language :: Python
Classifier: Programming Language :: Python :: 3
Classifier: Programming Language :: Python :: 3.8
Classifier: Programming Language :: Python :: 3.9
Classifier: Programming Language :: Python :: 3.10
Classifier: Programming Language :: Python :: 3.11
Classifier: Programming Language :: Python :: 3.12
Classifier: Programming Language :: Python :: 3.13
Requires-Python: >=3.8
License-File: LICENSE
Requires-Dist: rich
Requires-Dist: tqdm
Requires-Dist: torch>=1.7.0
Requires-Dist: xlsxwriter
Requires-Dist: polars>=1.8.2
Requires-Dist: numpy
Requires-Dist: pyyaml
Requires-Dist: pympler
Requires-Dist: typing_extensions
Provides-Extra: docs
Requires-Dist: mike; extra == "docs"
Requires-Dist: mkdocs; extra == "docs"
Requires-Dist: mkdocstrings[python]; extra == "docs"
Requires-Dist: mkdocs-material; extra == "docs"
Requires-Dist: mkdocs-jupyter; extra == "docs"
Requires-Dist: mkdocs-glightbox; extra == "docs"
Requires-Dist: mkdocs-inline-select-svg-plugin; extra == "docs"
Provides-Extra: test
Requires-Dist: ruff>=0.6.0; extra == "test"
Requires-Dist: mypy; extra == "test"
Requires-Dist: pytest; extra == "test"
Requires-Dist: pytest-cov; extra == "test"
Requires-Dist: pytest-xdist; extra == "test"
Dynamic: download-url
Dynamic: license-file
